README.md
setup.py
TOPSIS_Pulkit_101803334.egg-info/PKG-INFO
TOPSIS_Pulkit_101803334.egg-info/SOURCES.txt
TOPSIS_Pulkit_101803334.egg-info/dependency_links.txt
TOPSIS_Pulkit_101803334.egg-info/entry_points.txt
TOPSIS_Pulkit_101803334.egg-info/requires.txt
TOPSIS_Pulkit_101803334.egg-info/top_level.txt
src/topsis_pulkitsingla.py