Metadata-Version: 2.1
Name: TOPSIS-Pulkit-101803334
Version: 1.0.1
Summary: A Python package implementing TOPSIS technique.
Home-page: https://pypi.org/project/TOPSIS-Pulkit-101803334
Author: Pulkit Singla
Author-email: pulkitsingla1400@gmail.com
License: MIT
Platform: UNKNOWN
Classifier: License :: OSI Approved :: MIT License
Classifier: Programming Language :: Python :: 3
Classifier: Programming Language :: Python :: 3.4
Classifier: Programming Language :: Python :: 3.5
Classifier: Programming Language :: Python :: 3.6
Classifier: Programming Language :: Python :: 3.7
